<?xml version="1.0" encoding="utf-8"?><DOFFIN_ESENDERS xsi:noNamespaceSchemaLocation="DOFFIN_ESENDERS.xd" VERSION="V2.0.0" xmlns:xsi="http://www.w3.org/2001/XMLSchema-instance"><FORM_SECTION><VOLUNTARY_CONTRACT LG="NB" CATEGORY="ORIGINAL" FORM="102" VERSION="N2.0.0"><FD_VOLUNTARY_CONTRACT CTYPE="SERVICES"><CONTRACTING_AUTHORITY_INFORMATION><NAME_ADDRESSES_CONTACT_CONTRACT><CA_CE_CONCESSIONAIRE_PROFILE><ORGANISATION><OFFICIALNAME>Skatteetaten</OFFICIALNAME><NATIONALID>974761076</NATIONALID></ORGANISATION><ADDRESS>Fredrik Selmersvei 4</ADDRESS><TOWN>Oslo</TOWN><POSTAL_CODE>0667</POSTAL_CODE><COUNTRY VALUE="NO" /><ATTENTION>Finn Bjarne Østby</ATTENTION><PHONE>+47 80080000</PHONE><E_MAILS><E_MAIL>finn.ostby@skatteetaten.no</E_MAIL></E_MAILS></CA_CE_CONCESSIONAIRE_PROFILE><INTERNET_ADDRESSES_CONTRACT><URL_BUYER>https://kgv.doffin.no/ctm/Supplier/CompanyInformation/Index/1075</URL_BUYER><URL_INFORMATION>https://kgv.doffin.no/ctm/Supplier/Documents/Folder/127641</URL_INFORMATION></INTERNET_ADDRESSES_CONTRACT><FURTHER_INFORMATION><IDEM /></FURTHER_INFORMATION><SPECIFICATIONS_AND_ADDITIONAL_DOCUMENTS><IDEM /></SPECIFICATIONS_AND_ADDITIONAL_DOCUMENTS><TENDERS_REQUESTS_APPLICATIONS_MUST_BE_SENT_TO><CONTACT_DATA><ORGANISATION><OFFICIALNAME>Skatteetaten</OFFICIALNAME></ORGANISATION><ADDRESS>Fredrik Selmers vei 4</ADDRESS><TOWN>Oslo</TOWN><POSTAL_CODE>0663</POSTAL_CODE><COUNTRY VALUE="NO" /></CONTACT_DATA></TENDERS_REQUESTS_APPLICATIONS_MUST_BE_SENT_TO></NAME_ADDRESSES_CONTACT_CONTRACT><TYPE_AND_ACTIVITIES_AND_PURCHASING_ON_BEHALF><TYPE_AND_ACTIVITIES><TYPE_OF_ACTIVITY VALUE="GENERAL_PUBLIC_SERVICES" /></TYPE_AND_ACTIVITIES><PURCHASING_ON_BEHALF><PURCHASING_ON_BEHALF_NO /></PURCHASING_ON_BEHALF></TYPE_AND_ACTIVITIES_AND_PURCHASING_ON_BEHALF></CONTRACTING_AUTHORITY_INFORMATION><OBJECT_CONTRACT_INFORMATION><DESCRIPTION_CONTRACT_INFORMATION><TITLE_CONTRACT><P>Revisjonskoder tilknyttet årsregnskap</P></TITLE_CONTRACT><SHORT_CONTRACT_DESCRIPTION><P>Anskaffelsens formål er å inngå en avtale med leverandør som kan levere informasjon om revisjonsanmerkninger og revisjonsberetning tilknyttet årsregnskap.  </P></SHORT_CONTRACT_DESCRIPTION><CPV><CPV_MAIN><CPV_CODE CODE="79210000" /></CPV_MAIN></CPV></DESCRIPTION_CONTRACT_INFORMATION><NATURE_QUANTITY_SCOPE><COSTS_RANGE_AND_CURRENCY CURRENCY="NOK"><RANGE_VALUE_COST><LOW_VALUE>100000</LOW_VALUE><HIGH_VALUE>300000</HIGH_VALUE></RANGE_VALUE_COST></COSTS_RANGE_AND_CURRENCY></NATURE_QUANTITY_SCOPE><CONDITIONS_FOR_PARTICIPATION_F102><P>Tilbyder må ha oppfylt sine forpliktelser med hensyn til betaling av skatter og arbeidsgiveravgift .</P><P>Tilbyder må ha oppfylt sine forpliktelser med hensyn til betaling av merverdiavgift.</P><P>Tilbyder skal/vil oppfylle lovbestemte krav i Norge innen helse, miljø og sikkerhet (HMS).    </P></CONDITIONS_FOR_PARTICIPATION_F102></OBJECT_CONTRACT_INFORMATION><PROCEDURE_DEFINITION_CONTRACT_NOTICE><TYPE_OF_PROCEDURE><PT_VOL_NO_PREQUAL_NEGOTIATION /></TYPE_OF_PROCEDURE><ADMINISTRATIVE_INFORMATION_CONTRACT_NOTICE><FILE_REFERENCE_NUMBER><P>201550013</P></FILE_REFERENCE_NUMBER><RECEIPT_LIMIT_DATE><DAY>17</DAY><MONTH>03</MONTH><YEAR>2015</YEAR><TIME>12:00</TIME></RECEIPT_LIMIT_DATE><LANGUAGE><LANGUAGE_OTHER><P>Norsk</P></LANGUAGE_OTHER></LANGUAGE></ADMINISTRATIVE_INFORMATION_CONTRACT_NOTICE></PROCEDURE_DEFINITION_CONTRACT_NOTICE><COMPLEMENTARY_INFORMATION_CONTRACT_NOTICE><NOTICE_DISPATCH_DATE><DAY>26</DAY><MONTH>02</MONTH><YEAR>2015</YEAR></NOTICE_DISPATCH_DATE></COMPLEMENTARY_INFORMATION_CONTRACT_NOTICE></FD_VOLUNTARY_CONTRACT></VOLUNTARY_CONTRACT></FORM_SECTION><DOFFIN_APPENDIX><AUTHORITY_ORGANISATION_NR>974 761 076</AUTHORITY_ORGANISATION_NR><DOFFIN_FORM_TYPE><VOLUNTARY><LOCATION><COUNTIES><COUNTY code="0300" /></COUNTIES><MUNICIPALITIES><MUNICIPALITY code="301" /></MUNICIPALITIES></LOCATION><EXTERNAL_DOCUMENT_URL>https://kgv.doffin.no/ctm/Supplier/Documents/Folder/127641</EXTERNAL_DOCUMENT_URL><EXPRESSION_OF_INTEREST_URL>https://kgv.doffin.no/ctm/Supplier/Notice/265493</EXPRESSION_OF_INTEREST_URL></VOLUNTARY></DOFFIN_FORM_TYPE></DOFFIN_APPENDIX></DOFFIN_ESENDERS>